README.md
setup.py
tankerkoenig_api/__init__.py
tankerkoenig_api/station.py
tankerkoenig_api/tankerkoenig_api.py
tankerkoenig_api.egg-info/PKG-INFO
tankerkoenig_api.egg-info/SOURCES.txt
tankerkoenig_api.egg-info/dependency_links.txt
tankerkoenig_api.egg-info/requires.txt
tankerkoenig_api.egg-info/top_level.txt